arclia/happygame/__init__.py
arclia/happygame/assets.py
arclia/happygame/math.py
arclia/kerblaxion/__init__.py
arclia/kerblaxion/__main__.py
arclia/kerblaxion/game.py
arclia/kerblaxion/hero.py
arclia/kerblaxion/assets/__init__.py
arclia/kerblaxion/assets/__pycache__/__init__.cpython-310.pyc
arclia/kerblaxion/assets/fonts/OFL.txt
arclia/kerblaxion/assets/fonts/Silkscreen-Bold.ttf
arclia/kerblaxion/assets/fonts/Silkscreen-Regular.ttf
arclia/kerblaxion/assets/graphics/enemy01.png
arclia/kerblaxion/assets/graphics/explode01.png
arclia/kerblaxion/assets/graphics/explode02.png
arclia/kerblaxion/assets/graphics/explode03.png
arclia/kerblaxion/assets/graphics/explode04.png
arclia/kerblaxion/assets/graphics/hero/hero01.png
arclia/kerblaxion/assets/graphics/hero/hero02.png
arclia/kerblaxion/assets/graphics/hero/hero03.png
arclia/kerblaxion/assets/graphics/hero/hero04.png
arclia/kerblaxion/assets/graphics/hero/life.png
arclia/kerblaxion/assets/music/level01.mp3
arclia/kerblaxion/assets/sfx/hero-explode.wav
arclia/kerblaxion/assets/sfx/shoot.wav
arclia/kerblaxion/ui/__init__.py
arclia/kerblaxion/ui/score.py
arclia/pubsub/__init__.py
arclia/pubsub/_async.py
arclia/pubsub/_sync.py
kerblaxion-0.2.0.dist-info/METADATA
kerblaxion-0.2.0.dist-info/WHEEL
kerblaxion-0.2.0.dist-info/entry_points.txt
kerblaxion-0.2.0.dist-info/top_level.txt
kerblaxion-0.2.0.dist-info/RECORD
