Metadata-Version: 2.1
Name: kerblaxion
Version: 0.2.0
Summary: Space Invaders + Galaxian Clone
Home-page: UNKNOWN
License: UNKNOWN
Platform: UNKNOWN
Classifier: Programming Language :: Python :: 3
Classifier: Operating System :: OS Independent
Requires-Python: >=3.10
Requires-Dist: pygame (>=2.1.2)
